{
  "accentColor": "{{appsmith.theme.colors.primaryColor}}",
  "animateLoading": true,
  "autoFocus": false,
  "borderRadius": "{{appsmith.theme.borderRadius.appBorderRadius}}",
  "bottomRow": 8,
  "boxShadow": "none",
  "defaultText": "",
  "dynamicBindingPathList": [
    {
      "key": "accentColor"
    },
    {
      "key": "borderRadius"
    }
  ],
  "dynamicHeight": "AUTO_HEIGHT",
  "dynamicPropertyPathList": [
    {
      "key": "onSubmit"
    }
  ],
  "dynamicTriggerPathList": [
    {
      "key": "onTextChanged"
    },
    {
      "key": "onSubmit"
    }
  ],
  "errorMessage": "",
  "iconAlign": "left",
  "inputType": "TEXT",
  "isDisabled": false,
  "isLoading": false,
  "isRequired": false,
  "isSpellCheck": true,
  "isVisible": true,
  "key": "323cwn6f5x",
  "label": "名称",
  "labelAlignment": "left",
  "labelPosition": "Top",
  "labelStyle": "",
  "labelTextSize": "0.875rem",
  "labelWidth": 5,
  "leftColumn": 10,
  "maxDynamicHeight": 9000,
  "minDynamicHeight": 4,
  "minWidth": 450,
  "mobileBottomRow": 13,
  "mobileLeftColumn": 0,
  "mobileRightColumn": 20,
  "mobileTopRow": 6,
  "needsErrorInfo": false,
  "onBlur": "{{}}",
  "onSubmit": "{{Tab.enterfun()}}",
  "onTextChanged": "",
  "originalBottomRow": 8,
  "originalTopRow": 1,
  "parentColumnSpace": 20.25,
  "parentId": "0",
  "parentRowSpace": 10,
  "regex": "",
  "renderMode": "CANVAS",
  "resetOnSubmit": false,
  "responsiveBehavior": "fill",
  "rightColumn": 23,
  "shouldAllowAutofill": false,
  "showStepArrows": false,
  "topRow": 1,
  "type": "INPUT_WIDGET_V2",
  "version": 2,
  "widgetId": "qk19ive8ld",
  "widgetName": "Input19"
}