{
  "gitSyncId": "67bed107a0c78065eecac2b6_23686186-ea81-4bdb-8231-957d6003ed54",
  "id": "教材同步_getImageCopy",
  "pluginId": "restapi-plugin",
  "pluginType": "API",
  "unpublishedAction": {
    "actionConfiguration": {
      "autoGeneratedHeaders": [],
      "body": "",
      "bodyFormData": [],
      "encodeParamsToggle": true,
      "formData": {
        "apiContentType": "none"
      },
      "headers": [],
      "httpMethod": "GET",
      "httpVersion": "HTTP11",
      "paginationType": "NONE",
      "path": "images/tests/7.jpeg",
      "pluginSpecifiedTemplates": [
        {
          "value": false
        }
      ],
      "queryParameters": [],
      "timeoutInMillisecond": 10000
    },
    "confirmBeforeExecute": false,
    "datasource": {
      "id": "storage",
      "isAutoGenerated": false,
      "name": "storage",
      "pluginId": "restapi-plugin"
    },
    "dynamicBindingPathList": [],
    "executeOnLoad": false,
    "name": "getImageCopy",
    "pageId": "教材同步",
    "userSetOnLoad": false
  }
}